mips_core.v

`timescale 1ns/1ns

module mips_core (
    input clk1, 
    input clk2
);
    reg [31:0] PC, IF_ID_IR, IF_ID_NPC;
    reg [31:0] ID_EX_IR, ID_EX_NPC, ID_EX_A, ID_EX_B, ID_EX_Imm;
    reg [2:0]  ID_EX_type, EX_MEM_type, MEM_WB_type;
    reg [31:0] EX_MEM_IR, EX_MEM_ALUOut, EX_MEM_B;
    reg        EX_MEM_cond;
    reg [31:0] MEM_WB_IR, MEM_WB_ALUOut, MEM_WB_LMD;

    reg [31:0] Reg [0:31];
    reg [31:0] Mem [0:1023];

    reg halted;
    reg TAKEN_BRANCH;

    initial begin
        PC = 0;
        halted = 0;
        TAKEN_BRANCH = 0;
    end

    parameter RR_ALU = 3'b000, RM_ALU = 3'b001, LOAD = 3'b010, STORE = 3'b011, BRANCH = 3'b100, HALT = 3'b101;

    parameter ADD = 6'b000000, SUB = 6'b000001, AND = 6'b000010, OR = 6'b000011,
              SLT = 6'b000100, MUL = 6'b000101, HLT = 6'b111111, LW = 6'b001000,
              SW = 6'b001001, ADDI = 6'b001010, SUBI = 6'b001011, SLTI = 6'b001100,
              BNEQZ = 6'b001101, BEQZ = 6'b001110;

    always @(posedge clk1) begin
        if (halted == 0) begin
            if (((EX_MEM_IR[31:26] == BEQZ) && (EX_MEM_cond == 1'b1)) ||
                ((EX_MEM_IR[31:26] == BNEQZ) && (EX_MEM_cond == 1'b0))) begin
                IF_ID_IR     <= #2 Mem[EX_MEM_ALUOut];
                TAKEN_BRANCH <= #2 1'b1;
                IF_ID_NPC    <= #2 EX_MEM_ALUOut + 1;
                PC           <= #2 EX_MEM_ALUOut + 1;
            end else begin
                IF_ID_IR     <= #2 Mem[PC];
                IF_ID_NPC    <= #2 PC + 1;
                PC           <= #2 PC + 1;
            end
        end
    end

    always @(posedge clk2) begin
        if (halted == 0) begin
            if (IF_ID_IR[25:21] == 5'b00000) ID_EX_A <= 0;
            else ID_EX_A <= #2 Reg[IF_ID_IR[25:21]];

            if (IF_ID_IR[20:16] == 5'b00000) ID_EX_B <= 0;
            else ID_EX_B <= #2 Reg[IF_ID_IR[20:16]];

            ID_EX_NPC <= #2 IF_ID_NPC;
            ID_EX_IR  <= #2 IF_ID_IR;
            ID_EX_Imm <= #2 {{16{IF_ID_IR[15]}}, IF_ID_IR[15:0]};

            case (IF_ID_IR[31:26])
                ADD, SUB, AND, OR, SLT, MUL: ID_EX_type <= #2 RR_ALU;
                ADDI, SUBI, SLTI:            ID_EX_type <= #2 RM_ALU;
                LW:                          ID_EX_type <= #2 LOAD;
                SW:                          ID_EX_type <= #2 STORE;
                BNEQZ, BEQZ:                 ID_EX_type <= #2 BRANCH;
                HLT:                         ID_EX_type <= #2 HALT;
                default:                     ID_EX_type <= #2 HALT;
            endcase
        end
    end

    always @(posedge clk1) begin
        if (halted == 0) begin
            EX_MEM_IR    <= #2 ID_EX_IR;
            EX_MEM_type  <= #2 ID_EX_type;
            TAKEN_BRANCH <= #2 1'b0;

            case (ID_EX_type)
                RR_ALU: begin
                    case (ID_EX_IR[31:26])
                        ADD: EX_MEM_ALUOut <= #2 ID_EX_A + ID_EX_B;
                        SUB: EX_MEM_ALUOut <= #2 ID_EX_A - ID_EX_B;
                        AND: EX_MEM_ALUOut <= #2 ID_EX_A & ID_EX_B;
                        OR:  EX_MEM_ALUOut <= #2 ID_EX_A | ID_EX_B;
                        SLT: EX_MEM_ALUOut <= #2 (ID_EX_A < ID_EX_B);
                        MUL: EX_MEM_ALUOut <= #2 ID_EX_A * ID_EX_B;
                        default: EX_MEM_ALUOut <= #2 32'hxxxxxxxx;
                    endcase
                end

                RM_ALU: begin
                    case (ID_EX_IR[31:26])
                        ADDI: EX_MEM_ALUOut <= #2 ID_EX_A + ID_EX_Imm;
                        SUBI: EX_MEM_ALUOut <= #2 ID_EX_A - ID_EX_Imm;
                        SLTI: EX_MEM_ALUOut <= #2 (ID_EX_A < ID_EX_Imm);
                        default: EX_MEM_ALUOut <= #2 32'hxxxxxxxx;
                    endcase
                end

                LOAD, STORE: begin
                    EX_MEM_ALUOut <= #2 ID_EX_A + ID_EX_Imm;
                    EX_MEM_B      <= #2 ID_EX_B;
                end

                BRANCH: begin
                    EX_MEM_ALUOut <= #2 ID_EX_NPC + ID_EX_Imm;
                    EX_MEM_cond   <= #2 (ID_EX_A == 0);
                end
            endcase
        end
    end

    always @(posedge clk2) begin
        if (halted == 0) begin
            MEM_WB_IR   <= #2 EX_MEM_IR;
            MEM_WB_type <= #2 EX_MEM_type;

            case (EX_MEM_type)
                RR_ALU, RM_ALU: MEM_WB_ALUOut <= #2 EX_MEM_ALUOut;
                LOAD:           MEM_WB_LMD    <= #2 Mem[EX_MEM_ALUOut];
                STORE:          if (TAKEN_BRANCH == 0) Mem[EX_MEM_ALUOut] <= #2 EX_MEM_B;
            endcase
        end
    end

    always @(posedge clk1) begin
        if (TAKEN_BRANCH == 0) begin
            case (MEM_WB_type)
                RR_ALU: if (MEM_WB_IR[15:11] != 0) Reg[MEM_WB_IR[15:11]] <= #2 MEM_WB_ALUOut;
                RM_ALU: if (MEM_WB_IR[20:16] != 0) Reg[MEM_WB_IR[20:16]] <= #2 MEM_WB_ALUOut;
                LOAD:   if (MEM_WB_IR[20:16] != 0) Reg[MEM_WB_IR[20:16]] <= #2 MEM_WB_LMD;
                HALT:   halted <= #2 1'b1;
            endcase
        end
    end
endmodule

mips_tb.v

`timescale 1ns/1ns

module mips_tb;
    reg clk1, clk2;

    mips_core uut (
        .clk1(clk1),
        .clk2(clk2)
    );

    initial begin
        clk1 = 0;
        clk2 = 0;
        forever begin
            #5 clk1 = 1; #5 clk1 = 0;
            #5 clk2 = 1; #5 clk2 = 0;
        end
    end

    initial begin
        uut.Reg[0] = 32'h00000000;
        uut.Reg[1] = 32'h0000000A; // R1 = 10
        uut.Reg[2] = 32'h00000014; // R2 = 20

        uut.Mem[0] = 32'h00221800; // ADD R3, R1, R2
        uut.Mem[1] = 32'hfc000000; // HLT

        $dumpfile("mips.vcd");
        $dumpvars(0, mips_tb);

        #300 $finish;
    end
endmodule

mips.vcd
$date
	Sat Sep 26 16:08:47 2026
$end
$version
	Icarus Verilog
$end
$timescale
	1ns
$end
$scope module mips_tb $end
$var reg 1 ! clk1 $end
$var reg 1 " clk2 $end
$scope module uut $end
$var wire 1 ! clk1 $end
$var wire 1 " clk2 $end
$var parameter 6 # ADD $end
$var parameter 6 $ ADDI $end
$var parameter 6 % AND $end
$var parameter 6 & BEQZ $end
$var parameter 6 ' BNEQZ $end
$var parameter 3 ( BRANCH $end
$var parameter 3 ) HALT $end
$var parameter 6 * HLT $end
$var parameter 3 + LOAD $end
$var parameter 6 , LW $end
$var parameter 6 - MUL $end
$var parameter 6 . OR $end
$var parameter 3 / RM_ALU $end
$var parameter 3 0 RR_ALU $end
$var parameter 6 1 SLT $end
$var parameter 6 2 SLTI $end
$var parameter 3 3 STORE $end
$var parameter 6 4 SUB $end
$var parameter 6 5 SUBI $end
$var parameter 6 6 SW $end
$var reg 32 7 EX_MEM_ALUOut [31:0] $end
$var reg 32 8 EX_MEM_B [31:0] $end
$var reg 32 9 EX_MEM_IR [31:0] $end
$var reg 1 : EX_MEM_cond $end
$var reg 3 ; EX_MEM_type [2:0] $end
$var reg 32 < ID_EX_A [31:0] $end
$var reg 32 = ID_EX_B [31:0] $end
$var reg 32 > ID_EX_IR [31:0] $end
$var reg 32 ? ID_EX_Imm [31:0] $end
$var reg 32 @ ID_EX_NPC [31:0] $end
$var reg 3 A ID_EX_type [2:0] $end
$var reg 32 B IF_ID_IR [31:0] $end
$var reg 32 C IF_ID_NPC [31:0] $end
$var reg 32 D MEM_WB_ALUOut [31:0] $end
$var reg 32 E MEM_WB_IR [31:0] $end
$var reg 32 F MEM_WB_LMD [31:0] $end
$var reg 3 G MEM_WB_type [2:0] $end
$var reg 32 H PC [31:0] $end
$var reg 1 I TAKEN_BRANCH $end
$var reg 1 J halted $end
$upscope $end
$upscope $end
$enddefinitions $end
$comment Show the parameter values. $end
$dumpall
b1001 6
b1011 5
b1 4
b11 3
b1100 2
b100 1
b0 0
b1 /
b11 .
b101 -
b1000 ,
b10 +
b111111 *
b101 )
b100 (
b1101 '
b1110 &
b10 %
b1010 $
b0 #
$end
#0
$dumpvars
0J
0I
b0 H
bx G
bx F
bx E
bx D
bx C
bx B
bx A
bx @
bx ?
bx >
bx =
bx <
bx ;
x:
bx 9
bx 8
bx 7
0"
0!
$end
#5
1!
#7
b1 H
b1 C
b1000100001100000000000 B
#10
0!
#15
1"
#17
b0 A
b1100000000000 ?
b1000100001100000000000 >
b1 @
b10100 =
b1010 <
#20
0"
#25
1!
#27
b11110 7
b0 ;
b1000100001100000000000 9
b10 H
b10 C
b11111100000000000000000000000000 B
#30
0!
#35
b0 =
b0 <
1"
#37
b11110 D
b0 G
b1000100001100000000000 E
b101 A
b0 ?
b11111100000000000000000000000000 >
b10 @
#40
0"
#45
1!
#47
b11 H
b11 C
bx B
b101 ;
b11111100000000000000000000000000 9
#50
0!
#55
1"
#57
bx ?
bx >
b11 @
bx =
bx <
b101 G
b11111100000000000000000000000000 E
#60
0"
#65
1!
#67
1J
bx 9
b100 H
b100 C
